odoo/addons/web_editor_disable_chatgpt/README.rst
odoo/addons/web_editor_disable_chatgpt/__init__.py
odoo/addons/web_editor_disable_chatgpt/__manifest__.py
odoo/addons/web_editor_disable_chatgpt/i18n/it.po
odoo/addons/web_editor_disable_chatgpt/i18n/web_editor_disable_chatgpt.pot
odoo/addons/web_editor_disable_chatgpt/readme/CONTRIBUTORS.md
odoo/addons/web_editor_disable_chatgpt/readme/DESCRIPTION.md
odoo/addons/web_editor_disable_chatgpt/readme/ROADMAP.md
odoo/addons/web_editor_disable_chatgpt/static/description/icon.png
odoo/addons/web_editor_disable_chatgpt/static/description/index.html
odoo/addons/web_editor_disable_chatgpt/static/src/main/chatgpt/chatgpt_plugin_patch.esm.js
odoo/addons/web_editor_disable_chatgpt/static/tests/tours/html_editor_disable_chatgpt_tour.esm.js
odoo/addons/web_editor_disable_chatgpt/tests/__init__.py
odoo/addons/web_editor_disable_chatgpt/tests/test_tours.py
odoo_addon_web_editor_disable_chatgpt-18.0.1.0.0.3.dist-info/METADATA
odoo_addon_web_editor_disable_chatgpt-18.0.1.0.0.3.dist-info/WHEEL
odoo_addon_web_editor_disable_chatgpt-18.0.1.0.0.3.dist-info/top_level.txt
odoo_addon_web_editor_disable_chatgpt-18.0.1.0.0.3.dist-info/RECORD
